<?xml version="1.0" encoding="UTF-8"?><font><info face="SFPFSCProText-Semibold" size="42" bold="0" italic="0" charset="" unicode="1" stretchH="100" smooth="1" aa="1" padding="1,1,1,1" spacing="1,1"/><common lineHeight="42" base="40" scaleW="619" scaleH="619" pages="1" packed="0"/><pages><page id="0" file="sf-pro-bold-zh.png"/></pages><chars count="271"><char id="32" x="0" y="0" width="0" height="0" xoffset="0" yoffset="-6" xadvance="12" page="0" chnl="15"/><!--   --><char id="33" x="585" y="387" width="10" height="33" xoffset="2" yoffset="3" xadvance="15" page="0" chnl="15"/><!-- ! --><char id="34" x="543" y="602" width="16" height="14" xoffset="2" yoffset="3" xadvance="20" page="0" chnl="15"/><!-- " --><char id="35" x="506" y="431" width="29" height="32" xoffset="-1" yoffset="3" xadvance="28" page="0" chnl="15"/><!-- # --><char id="36" x="543" y="401" width="25" height="38" xoffset="2" yoffset="0" xadvance="29" page="0" chnl="15"/><!-- $ --><char id="37" x="507" y="26" width="34" height="33" xoffset="0" yoffset="3" xadvance="35" page="0" chnl="15"/><!-- % --><char id="38" x="506" y="264" width="30" height="33" xoffset="1" yoffset="3" xadvance="31" page="0" chnl="15"/><!-- & --><char id="39" x="451" y="598" width="7" height="15" xoffset="2" yoffset="3" xadvance="12" page="0" chnl="15"/><!-- ' --><char id="40" x="597" y="455" width="13" height="39" xoffset="3" yoffset="2" xadvance="18" page="0" chnl="15"/><!-- ( --><char id="41" x="597" y="495" width="13" height="39" xoffset="1" yoffset="2" xadvance="18" page="0" chnl="15"/><!-- ) --><char id="42" x="185" y="596" width="18" height="18" xoffset="2" yoffset="3" xadvance="22" page="0" chnl="15"/><!-- * --><char id="43" x="543" y="474" width="25" height="24" xoffset="2" yoffset="10" xadvance="29" page="0" chnl="15"/><!-- + --><char id="44" x="204" y="596" width="9" height="15" xoffset="2" yoffset="28" xadvance="14" page="0" chnl="15"/><!-- , --><char id="45" x="597" y="432" width="16" height="8" xoffset="2" yoffset="18" xadvance="21" page="0" chnl="15"/><!-- - --><char id="46" x="74" y="605" width="9" height="8" xoffset="2" yoffset="27" xadvance="14" page="0" chnl="15"/><!-- . --><char id="47" x="597" y="278" width="18" height="39" xoffset="-1" yoffset="2" xadvance="16" page="0" chnl="15"/><!-- / --><char id="48" x="543" y="99" width="26" height="33" xoffset="1" yoffset="3" xadvance="28" page="0" chnl="15"/><!-- 0 --><char id="49" x="0" y="587" width="16" height="32" xoffset="1" yoffset="3" xadvance="21" page="0" chnl="15"/><!-- 1 --><char id="50" x="89" y="587" width="23" height="32" xoffset="2" yoffset="3" xadvance="27" page="0" chnl="15"/><!-- 2 --><char id="51" x="543" y="440" width="25" height="33" xoffset="1" yoffset="3" xadvance="28" page="0" chnl="15"/><!-- 3 --><char id="52" x="543" y="269" width="26" height="32" xoffset="1" yoffset="3" xadvance="29" page="0" chnl="15"/><!-- 4 --><char id="53" x="543" y="534" width="24" height="33" xoffset="2" yoffset="3" xadvance="28" page="0" chnl="15"/><!-- 5 --><char id="54" x="543" y="133" width="26" height="33" xoffset="1" yoffset="3" xadvance="29" page="0" chnl="15"/><!-- 6 --><char id="55" x="572" y="34" width="24" height="32" xoffset="0" yoffset="3" xadvance="25" page="0" chnl="15"/><!-- 7 --><char id="56" x="543" y="167" width="26" height="33" xoffset="1" yoffset="3" xadvance="29" page="0" chnl="15"/><!-- 8 --><char id="57" x="543" y="201" width="26" height="33" xoffset="1" yoffset="3" xadvance="29" page="0" chnl="15"/><!-- 9 --><char id="58" x="175" y="596" width="9" height="23" xoffset="2" yoffset="12" xadvance="14" page="0" chnl="15"/><!-- : --><char id="59" x="46" y="588" width="10" height="31" xoffset="1" yoffset="12" xadvance="14" page="0" chnl="15"/><!-- ; --><char id="61" x="426" y="598" width="24" height="16" xoffset="2" yoffset="14" xadvance="29" page="0" chnl="15"/><!-- = --><char id="63" x="597" y="34" width="22" height="33" xoffset="0" yoffset="3" xadvance="23" page="0" chnl="15"/><!-- ? --><char id="64" x="467" y="530" width="36" height="37" xoffset="2" yoffset="3" xadvance="39" page="0" chnl="15"/><!-- @ --><char id="65" x="506" y="298" width="30" height="32" xoffset="0" yoffset="3" xadvance="30" page="0" chnl="15"/><!-- A --><char id="66" x="543" y="302" width="26" height="32" xoffset="2" yoffset="3" xadvance="29" page="0" chnl="15"/><!-- B --><char id="67" x="506" y="331" width="29" height="33" xoffset="1" yoffset="3" xadvance="31" page="0" chnl="15"/><!-- C --><char id="68" x="506" y="498" width="28" height="32" xoffset="2" yoffset="3" xadvance="32" page="0" chnl="15"/><!-- D --><char id="69" x="597" y="68" width="22" height="32" xoffset="2" yoffset="3" xadvance="26" page="0" chnl="15"/><!-- E --><char id="70" x="597" y="101" width="22" height="32" xoffset="2" yoffset="3" xadvance="25" page="0" chnl="15"/><!-- F --><char id="71" x="506" y="230" width="30" height="33" xoffset="1" yoffset="3" xadvance="32" page="0" chnl="15"/><!-- G --><char id="72" x="506" y="531" width="28" height="32" xoffset="2" yoffset="3" xadvance="33" page="0" chnl="15"/><!-- H --><char id="73" x="113" y="587" width="8" height="32" xoffset="2" yoffset="3" xadvance="13" page="0" chnl="15"/><!-- I --><char id="74" x="597" y="0" width="22" height="33" xoffset="0" yoffset="3" xadvance="25" page="0" chnl="15"/><!-- J --><char id="75" x="543" y="33" width="27" height="32" xoffset="2" yoffset="3" xadvance="30" page="0" chnl="15"/><!-- K --><char id="76" x="597" y="134" width="22" height="32" xoffset="2" yoffset="3" xadvance="25" page="0" chnl="15"/><!-- L --><char id="77" x="507" y="60" width="34" height="32" xoffset="2" yoffset="3" xadvance="38" page="0" chnl="15"/><!-- M --><char id="78" x="506" y="564" width="28" height="32" xoffset="2" yoffset="3" xadvance="32" page="0" chnl="15"/><!-- N --><char id="79" x="506" y="196" width="31" height="33" xoffset="1" yoffset="3" xadvance="33" page="0" chnl="15"/><!-- O --><char id="80" x="17" y="587" width="25" height="32" xoffset="2" yoffset="3" xadvance="28" page="0" chnl="15"/><!-- P --><char id="81" x="506" y="160" width="31" height="35" xoffset="1" yoffset="3" xadvance="33" page="0" chnl="15"/><!-- Q --><char id="82" x="543" y="335" width="26" height="32" xoffset="2" yoffset="3" xadvance="29" page="0" chnl="15"/><!-- R --><char id="83" x="543" y="235" width="26" height="33" xoffset="1" yoffset="3" xadvance="28" page="0" chnl="15"/><!-- S --><char id="84" x="543" y="66" width="27" height="32" xoffset="0" yoffset="3" xadvance="28" page="0" chnl="15"/><!-- T --><char id="85" x="506" y="464" width="28" height="33" xoffset="2" yoffset="3" xadvance="32" page="0" chnl="15"/><!-- U --><char id="86" x="506" y="365" width="29" height="32" xoffset="0" yoffset="3" xadvance="30" page="0" chnl="15"/><!-- V --><char id="87" x="302" y="587" width="40" height="32" xoffset="1" yoffset="3" xadvance="42" page="0" chnl="15"/><!-- W --><char id="88" x="543" y="0" width="28" height="32" xoffset="1" yoffset="3" xadvance="30" page="0" chnl="15"/><!-- X --><char id="89" x="506" y="398" width="29" height="32" xoffset="0" yoffset="3" xadvance="29" page="0" chnl="15"/><!-- Y --><char id="90" x="543" y="368" width="26" height="32" xoffset="1" yoffset="3" xadvance="29" page="0" chnl="15"/><!-- Z --><char id="91" x="597" y="535" width="13" height="39" xoffset="4" yoffset="2" xadvance="18" page="0" chnl="15"/><!-- [ --><char id="93" x="597" y="575" width="13" height="39" xoffset="0" yoffset="2" xadvance="18" page="0" chnl="15"/><!-- ] --><char id="94" x="506" y="597" width="20" height="15" xoffset="1" yoffset="4" xadvance="22" page="0" chnl="15"/><!-- ^ --><char id="95" x="385" y="613" width="22" height="6" xoffset="-1" yoffset="35" xadvance="20" page="0" chnl="15"/><!-- _ --><char id="97" x="218" y="589" width="22" height="25" xoffset="1" yoffset="10" xadvance="25" page="0" chnl="15"/><!-- a --><char id="98" x="543" y="568" width="24" height="33" xoffset="2" yoffset="2" xadvance="27" page="0" chnl="15"/><!-- b --><char id="99" x="572" y="285" width="23" height="25" xoffset="1" yoffset="10" xadvance="25" page="0" chnl="15"/><!-- c --><char id="100" x="572" y="0" width="24" height="33" xoffset="1" yoffset="2" xadvance="27" page="0" chnl="15"/><!-- d --><char id="101" x="572" y="311" width="23" height="25" xoffset="1" yoffset="10" xadvance="25" page="0" chnl="15"/><!-- e --><char id="102" x="597" y="398" width="16" height="33" xoffset="0" yoffset="2" xadvance="17" page="0" chnl="15"/><!-- f --><char id="103" x="543" y="499" width="24" height="34" xoffset="1" yoffset="10" xadvance="27" page="0" chnl="15"/><!-- g --><char id="104" x="572" y="217" width="23" height="33" xoffset="2" yoffset="2" xadvance="27" page="0" chnl="15"/><!-- h --><char id="105" x="585" y="421" width="9" height="34" xoffset="1" yoffset="1" xadvance="12" page="0" chnl="15"/><!-- i --><char id="106" x="572" y="387" width="12" height="42" xoffset="-2" yoffset="1" xadvance="12" page="0" chnl="15"/><!-- j --><char id="107" x="572" y="251" width="23" height="33" xoffset="2" yoffset="2" xadvance="25" page="0" chnl="15"/><!-- k --><char id="108" x="585" y="481" width="8" height="33" xoffset="2" yoffset="2" xadvance="12" page="0" chnl="15"/><!-- l --><char id="109" x="507" y="0" width="35" height="25" xoffset="2" yoffset="10" xadvance="39" page="0" chnl="15"/><!-- m --><char id="110" x="597" y="167" width="22" height="25" xoffset="2" yoffset="10" xadvance="26" page="0" chnl="15"/><!-- n --><char id="111" x="572" y="166" width="24" height="25" xoffset="1" yoffset="10" xadvance="26" page="0" chnl="15"/><!-- o --><char id="112" x="572" y="67" width="24" height="32" xoffset="2" yoffset="10" xadvance="27" page="0" chnl="15"/><!-- p --><char id="113" x="572" y="100" width="24" height="32" xoffset="1" yoffset="10" xadvance="27" page="0" chnl="15"/><!-- q --><char id="114" x="241" y="589" width="16" height="25" xoffset="2" yoffset="10" xadvance="18" page="0" chnl="15"/><!-- r --><char id="115" x="597" y="227" width="21" height="25" xoffset="1" yoffset="10" xadvance="24" page="0" chnl="15"/><!-- s --><char id="116" x="57" y="588" width="16" height="30" xoffset="0" yoffset="5" xadvance="17" page="0" chnl="15"/><!-- t --><char id="117" x="572" y="337" width="23" height="24" xoffset="1" yoffset="11" xadvance="26" page="0" chnl="15"/><!-- u --><char id="118" x="572" y="192" width="24" height="24" xoffset="0" yoffset="11" xadvance="24" page="0" chnl="15"/><!-- v --><char id="119" x="507" y="93" width="34" height="24" xoffset="0" yoffset="11" xadvance="35" page="0" chnl="15"/><!-- w --><char id="120" x="572" y="362" width="23" height="24" xoffset="0" yoffset="11" xadvance="24" page="0" chnl="15"/><!-- x --><char id="121" x="572" y="133" width="24" height="32" xoffset="0" yoffset="11" xadvance="25" page="0" chnl="15"/><!-- y --><char id="122" x="597" y="253" width="21" height="24" xoffset="1" yoffset="11" xadvance="24" page="0" chnl="15"/><!-- z --><char id="123" x="597" y="318" width="17" height="39" xoffset="0" yoffset="2" xadvance="18" page="0" chnl="15"/><!-- { --><char id="124" x="585" y="515" width="7" height="40" xoffset="4" yoffset="2" xadvance="16" page="0" chnl="15"/><!-- | --><char id="125" x="597" y="358" width="17" height="39" xoffset="0" yoffset="2" xadvance="18" page="0" chnl="15"/><!-- } --><char id="8230" x="467" y="607" width="32" height="8" xoffset="2" yoffset="27" xadvance="37" page="0" chnl="15"/><!-- … --><char id="8470" x="0" y="0" width="45" height="32" xoffset="2" yoffset="3" xadvance="48" page="0" chnl="15"/><!-- № --><char id="12290" x="597" y="441" width="15" height="13" xoffset="3" yoffset="27" xadvance="42" page="0" chnl="15"/><!-- 。 --><char id="19968" x="175" y="158" width="42" height="7" xoffset="0" yoffset="15" xadvance="42" page="0" chnl="15"/><!-- 一 --><char id="19978" x="426" y="240" width="40" height="39" xoffset="1" yoffset="-1" xadvance="42" page="0" chnl="15"/><!-- 上 --><char id="19979" x="385" y="573" width="40" height="39" xoffset="1" yoffset="0" xadvance="42" page="0" chnl="15"/><!-- 下 --><char id="19981" x="260" y="538" width="41" height="39" xoffset="0" yoffset="0" xadvance="42" page="0" chnl="15"/><!-- 不 --><char id="20004" x="426" y="280" width="40" height="39" xoffset="1" yoffset="0" xadvance="42" page="0" chnl="15"/><!-- 两 --><char id="20010" x="0" y="461" width="42" height="41" xoffset="0" yoffset="-2" xadvance="42" page="0" chnl="15"/><!-- 个 --><char id="20013" x="467" y="160" width="38" height="42" xoffset="2" yoffset="-2" xadvance="42" page="0" chnl="15"/><!-- 中 --><char id="20027" x="385" y="205" width="40" height="40" xoffset="1" yoffset="-2" xadvance="42" page="0" chnl="15"/><!-- 主 --><char id="20040" x="260" y="578" width="39" height="41" xoffset="1" yoffset="-2" xadvance="42" page="0" chnl="15"/><!-- 么 --><char id="20102" x="467" y="568" width="35" height="38" xoffset="3" yoffset="1" xadvance="42" page="0" chnl="15"/><!-- 了 --><char id="20108" x="344" y="586" width="40" height="33" xoffset="1" yoffset="3" xadvance="42" page="0" chnl="15"/><!-- 二 --><char id="20139" x="89" y="294" width="42" height="41" xoffset="0" yoffset="-2" xadvance="42" page="0" chnl="15"/><!-- 享 --><char id="20142" x="302" y="292" width="40" height="42" xoffset="1" yoffset="-2" xadvance="42" page="0" chnl="15"/><!-- 亮 --><char id="20160" x="0" y="419" width="42" height="41" xoffset="0" yoffset="-2" xadvance="42" page="0" chnl="15"/><!-- 什 --><char id="20174" x="132" y="164" width="42" height="40" xoffset="0" yoffset="-1" xadvance="42" page="0" chnl="15"/><!-- 从 --><char id="20197" x="385" y="369" width="40" height="40" xoffset="2" yoffset="-1" xadvance="42" page="0" chnl="15"/><!-- 以 --><char id="20219" x="89" y="420" width="42" height="41" xoffset="0" yoffset="-2" xadvance="42" page="0" chnl="15"/><!-- 任 --><char id="20241" x="89" y="84" width="42" height="41" xoffset="0" yoffset="-2" xadvance="42" page="0" chnl="15"/><!-- 休 --><char id="20250" x="46" y="336" width="42" height="41" xoffset="0" yoffset="-2" xadvance="42" page="0" chnl="15"/><!-- 会 --><char id="20309" x="46" y="378" width="42" height="41" xoffset="0" yoffset="-2" xadvance="42" page="0" chnl="15"/><!-- 何 --><char id="20320" x="260" y="126" width="41" height="41" xoffset="0" yoffset="-2" xadvance="42" page="0" chnl="15"/><!-- 你 --><char id="20339" x="46" y="168" width="42" height="41" xoffset="0" yoffset="-2" xadvance="42" page="0" chnl="15"/><!-- 佳 --><char id="20351" x="0" y="291" width="42" height="42" xoffset="0" yoffset="-2" xadvance="42" page="0" chnl="15"/><!-- 使 --><char id="20837" x="218" y="505" width="41" height="41" xoffset="0" yoffset="-2" xadvance="42" page="0" chnl="15"/><!-- 入 --><char id="20840" x="132" y="410" width="42" height="40" xoffset="0" yoffset="-2" xadvance="42" page="0" chnl="15"/><!-- 全 --><char id="20851" x="344" y="294" width="40" height="41" xoffset="1" yoffset="-2" xadvance="42" page="0" chnl="15"/><!-- 关 --><char id="20869" x="467" y="329" width="38" height="41" xoffset="2" yoffset="-2" xadvance="42" page="0" chnl="15"/><!-- 内 --><char id="20987" x="344" y="545" width="40" height="40" xoffset="1" yoffset="-1" xadvance="42" page="0" chnl="15"/><!-- 击 --><char id="20998" x="385" y="123" width="40" height="40" xoffset="1" yoffset="-1" xadvance="42" page="0" chnl="15"/><!-- 分 --><char id="21015" x="385" y="492" width="40" height="40" xoffset="1" yoffset="-1" xadvance="42" page="0" chnl="15"/><!-- 列 --><char id="21017" x="218" y="85" width="41" height="41" xoffset="0" yoffset="-1" xadvance="42" page="0" chnl="15"/><!-- 则 --><char id="21033" x="302" y="461" width="40" height="41" xoffset="0" yoffset="-2" xadvance="42" page="0" chnl="15"/><!-- 利 --><char id="21040" x="385" y="287" width="40" height="40" xoffset="1" yoffset="-1" xadvance="42" page="0" chnl="15"/><!-- 到 --><char id="21152" x="344" y="42" width="40" height="41" xoffset="0" yoffset="-1" xadvance="42" page="0" chnl="15"/><!-- 加 --><char id="21153" x="218" y="0" width="41" height="42" xoffset="1" yoffset="-2" xadvance="42" page="0" chnl="15"/><!-- 务 --><char id="21160" x="218" y="127" width="41" height="41" xoffset="0" yoffset="-1" xadvance="42" page="0" chnl="15"/><!-- 动 --><char id="21319" x="344" y="420" width="40" height="41" xoffset="1" yoffset="-1" xadvance="42" page="0" chnl="15"/><!-- 升 --><char id="21333" x="302" y="206" width="40" height="42" xoffset="1" yoffset="-2" xadvance="42" page="0" chnl="15"/><!-- 单 --><char id="21345" x="385" y="246" width="40" height="40" xoffset="1" yoffset="-1" xadvance="42" page="0" chnl="15"/><!-- 卡 --><char id="21407" x="302" y="0" width="41" height="39" xoffset="0" yoffset="0" xadvance="42" page="0" chnl="15"/><!-- 原 --><char id="21451" x="302" y="335" width="40" height="41" xoffset="1" yoffset="-1" xadvance="42" page="0" chnl="15"/><!-- 友 --><char id="21457" x="175" y="381" width="41" height="42" xoffset="0" yoffset="-2" xadvance="42" page="0" chnl="15"/><!-- 发 --><char id="21462" x="260" y="333" width="41" height="40" xoffset="1" yoffset="0" xadvance="42" page="0" chnl="15"/><!-- 取 --><char id="21487" x="426" y="320" width="40" height="38" xoffset="1" yoffset="1" xadvance="42" page="0" chnl="15"/><!-- 可 --><char id="21512" x="89" y="168" width="42" height="41" xoffset="0" yoffset="-2" xadvance="42" page="0" chnl="15"/><!-- 合 --><char id="21578" x="132" y="123" width="42" height="40" xoffset="0" yoffset="-1" xadvance="42" page="0" chnl="15"/><!-- 告 --><char id="22235" x="467" y="450" width="38" height="38" xoffset="2" yoffset="1" xadvance="42" page="0" chnl="15"/><!-- 四 --><char id="22238" x="467" y="411" width="38" height="38" xoffset="2" yoffset="1" xadvance="42" page="0" chnl="15"/><!-- 回 --><char id="22256" x="467" y="371" width="38" height="39" xoffset="2" yoffset="0" xadvance="42" page="0" chnl="15"/><!-- 困 --><char id="22312" x="218" y="337" width="41" height="41" xoffset="0" yoffset="-2" xadvance="42" page="0" chnl="15"/><!-- 在 --><char id="22330" x="302" y="80" width="41" height="39" xoffset="0" yoffset="0" xadvance="42" page="0" chnl="15"/><!-- 场 --><char id="22343" x="218" y="295" width="41" height="41" xoffset="0" yoffset="-2" xadvance="42" page="0" chnl="15"/><!-- 均 --><char id="22768" x="302" y="377" width="40" height="41" xoffset="1" yoffset="-1" xadvance="42" page="0" chnl="15"/><!-- 声 --><char id="22823" x="89" y="42" width="42" height="41" xoffset="0" yoffset="-1" xadvance="42" page="0" chnl="15"/><!-- 大 --><char id="22826" x="132" y="82" width="42" height="40" xoffset="0" yoffset="-1" xadvance="42" page="0" chnl="15"/><!-- 太 --><char id="22833" x="385" y="41" width="40" height="40" xoffset="1" yoffset="-1" xadvance="42" page="0" chnl="15"/><!-- 失 --><char id="22871" x="385" y="410" width="40" height="40" xoffset="1" yoffset="-1" xadvance="42" page="0" chnl="15"/><!-- 套 --><char id="22909" x="175" y="252" width="41" height="42" xoffset="1" yoffset="-2" xadvance="42" page="0" chnl="15"/><!-- 好 --><char id="22914" x="426" y="515" width="39" height="41" xoffset="1" yoffset="-2" xadvance="42" page="0" chnl="15"/><!-- 如 --><char id="22987" x="175" y="424" width="41" height="42" xoffset="0" yoffset="-2" xadvance="42" page="0" chnl="15"/><!-- 始 --><char id="23427" x="385" y="328" width="40" height="40" xoffset="1" yoffset="-2" xadvance="42" page="0" chnl="15"/><!-- 它 --><char id="23436" x="175" y="166" width="41" height="42" xoffset="1" yoffset="-2" xadvance="42" page="0" chnl="15"/><!-- 完 --><char id="23450" x="218" y="421" width="41" height="41" xoffset="0" yoffset="-2" xadvance="42" page="0" chnl="15"/><!-- 定 --><char id="23454" x="302" y="163" width="40" height="42" xoffset="1" yoffset="-2" xadvance="42" page="0" chnl="15"/><!-- 实 --><char id="23545" x="218" y="253" width="41" height="41" xoffset="1" yoffset="-2" xadvance="42" page="0" chnl="15"/><!-- 对 --><char id="23558" x="46" y="420" width="42" height="41" xoffset="0" yoffset="-2" xadvance="42" page="0" chnl="15"/><!-- 将 --><char id="23567" x="132" y="328" width="42" height="40" xoffset="0" yoffset="-1" xadvance="42" page="0" chnl="15"/><!-- 小 --><char id="23616" x="426" y="80" width="40" height="39" xoffset="0" yoffset="0" xadvance="42" page="0" chnl="15"/><!-- 局 --><char id="24050" x="467" y="121" width="39" height="38" xoffset="2" yoffset="0" xadvance="42" page="0" chnl="15"/><!-- 已 --><char id="24178" x="426" y="476" width="40" height="38" xoffset="1" yoffset="1" xadvance="42" page="0" chnl="15"/><!-- 干 --><char id="24179" x="426" y="120" width="40" height="39" xoffset="1" yoffset="0" xadvance="42" page="0" chnl="15"/><!-- 平 --><char id="24191" x="175" y="467" width="41" height="42" xoffset="0" yoffset="-2" xadvance="42" page="0" chnl="15"/><!-- 广 --><char id="24207" x="218" y="547" width="41" height="41" xoffset="0" yoffset="-2" xadvance="42" page="0" chnl="15"/><!-- 序 --><char id="24211" x="46" y="546" width="42" height="41" xoffset="0" yoffset="-2" xadvance="42" page="0" chnl="15"/><!-- 库 --><char id="24230" x="175" y="553" width="41" height="42" xoffset="0" yoffset="-2" xadvance="42" page="0" chnl="15"/><!-- 度 --><char id="24314" x="344" y="378" width="40" height="41" xoffset="1" yoffset="-2" xadvance="42" page="0" chnl="15"/><!-- 建 --><char id="24320" x="426" y="359" width="40" height="38" xoffset="1" yoffset="1" xadvance="42" page="0" chnl="15"/><!-- 开 --><char id="24335" x="385" y="0" width="40" height="40" xoffset="1" yoffset="-1" xadvance="42" page="0" chnl="15"/><!-- 式 --><char id="24352" x="218" y="169" width="41" height="41" xoffset="1" yoffset="-1" xadvance="42" page="0" chnl="15"/><!-- 张 --><char id="24418" x="132" y="205" width="42" height="40" xoffset="0" yoffset="-1" xadvance="42" page="0" chnl="15"/><!-- 形 --><char id="24471" x="46" y="126" width="42" height="41" xoffset="0" yoffset="-2" xadvance="42" page="0" chnl="15"/><!-- 得 --><char id="24687" x="344" y="336" width="40" height="41" xoffset="1" yoffset="-2" xadvance="42" page="0" chnl="15"/><!-- 息 --><char id="24744" x="89" y="336" width="42" height="41" xoffset="0" yoffset="-2" xadvance="42" page="0" chnl="15"/><!-- 您 --><char id="25103" x="260" y="210" width="41" height="40" xoffset="0" yoffset="-1" xadvance="42" page="0" chnl="15"/><!-- 戏 --><char id="25104" x="0" y="503" width="42" height="41" xoffset="0" yoffset="-2" xadvance="42" page="0" chnl="15"/><!-- 成 --><char id="25277" x="260" y="497" width="41" height="40" xoffset="0" yoffset="-1" xadvance="42" page="0" chnl="15"/><!-- 抽 --><char id="25454" x="132" y="0" width="42" height="40" xoffset="0" yoffset="-1" xadvance="42" page="0" chnl="15"/><!-- 据 --><char id="25552" x="260" y="251" width="41" height="40" xoffset="0" yoffset="-1" xadvance="42" page="0" chnl="15"/><!-- 提 --><char id="25928" x="0" y="33" width="42" height="42" xoffset="0" yoffset="-2" xadvance="42" page="0" chnl="15"/><!-- 效 --><char id="25968" x="175" y="295" width="41" height="42" xoffset="1" yoffset="-2" xadvance="42" page="0" chnl="15"/><!-- 数 --><char id="25972" x="260" y="84" width="41" height="41" xoffset="0" yoffset="-2" xadvance="42" page="0" chnl="15"/><!-- 整 --><char id="26032" x="0" y="162" width="42" height="42" xoffset="0" yoffset="-2" xadvance="42" page="0" chnl="15"/><!-- 新 --><char id="26053" x="89" y="462" width="42" height="41" xoffset="0" yoffset="-2" xadvance="42" page="0" chnl="15"/><!-- 旅 --><char id="26087" x="467" y="489" width="37" height="40" xoffset="3" yoffset="-1" xadvance="42" page="0" chnl="15"/><!-- 旧 --><char id="26102" x="260" y="292" width="41" height="40" xoffset="1" yoffset="-1" xadvance="42" page="0" chnl="15"/><!-- 时 --><char id="26159" x="385" y="533" width="40" height="39" xoffset="1" yoffset="0" xadvance="42" page="0" chnl="15"/><!-- 是 --><char id="26223" x="426" y="160" width="40" height="39" xoffset="1" yoffset="0" xadvance="42" page="0" chnl="15"/><!-- 景 --><char id="26368" x="385" y="82" width="40" height="40" xoffset="1" yoffset="0" xadvance="42" page="0" chnl="15"/><!-- 最 --><char id="26377" x="344" y="0" width="40" height="41" xoffset="1" yoffset="-2" xadvance="42" page="0" chnl="15"/><!-- 有 --><char id="26463" x="132" y="369" width="42" height="40" xoffset="0" yoffset="-1" xadvance="42" page="0" chnl="15"/><!-- 束 --><char id="26827" x="89" y="0" width="42" height="41" xoffset="0" yoffset="-1" xadvance="42" page="0" chnl="15"/><!-- 棋 --><char id="26834" x="46" y="210" width="42" height="41" xoffset="0" yoffset="-2" xadvance="42" page="0" chnl="15"/><!-- 棒 --><char id="27169" x="46" y="42" width="42" height="41" xoffset="0" yoffset="-1" xadvance="42" page="0" chnl="15"/><!-- 模 --><char id="27425" x="0" y="205" width="42" height="42" xoffset="0" yoffset="-2" xadvance="42" page="0" chnl="15"/><!-- 次 --><char id="27491" x="426" y="398" width="40" height="38" xoffset="1" yoffset="0" xadvance="42" page="0" chnl="15"/><!-- 正 --><char id="27492" x="175" y="40" width="42" height="39" xoffset="0" yoffset="-1" xadvance="42" page="0" chnl="15"/><!-- 此 --><char id="27493" x="302" y="120" width="40" height="42" xoffset="1" yoffset="-2" xadvance="42" page="0" chnl="15"/><!-- 步 --><char id="27604" x="467" y="81" width="39" height="39" xoffset="2" yoffset="-1" xadvance="42" page="0" chnl="15"/><!-- 比 --><char id="27809" x="46" y="294" width="42" height="41" xoffset="0" yoffset="-1" xadvance="42" page="0" chnl="15"/><!-- 没 --><char id="28040" x="426" y="557" width="39" height="40" xoffset="1" yoffset="-1" xadvance="42" page="0" chnl="15"/><!-- 消 --><char id="28155" x="132" y="287" width="42" height="40" xoffset="0" yoffset="-1" xadvance="42" page="0" chnl="15"/><!-- 添 --><char id="28165" x="260" y="456" width="41" height="40" xoffset="1" yoffset="-1" xadvance="42" page="0" chnl="15"/><!-- 清 --><char id="28216" x="0" y="377" width="42" height="41" xoffset="0" yoffset="-2" xadvance="42" page="0" chnl="15"/><!-- 游 --><char id="28418" x="132" y="492" width="42" height="40" xoffset="0" yoffset="-1" xadvance="42" page="0" chnl="15"/><!-- 漂 --><char id="28857" x="302" y="419" width="40" height="41" xoffset="1" yoffset="-1" xadvance="42" page="0" chnl="15"/><!-- 点 --><char id="29255" x="467" y="0" width="39" height="40" xoffset="2" yoffset="-1" xadvance="42" page="0" chnl="15"/><!-- 片 --><char id="29260" x="0" y="76" width="42" height="42" xoffset="0" yoffset="-2" xadvance="42" page="0" chnl="15"/><!-- 牌 --><char id="29609" x="175" y="80" width="42" height="38" xoffset="0" yoffset="1" xadvance="42" page="0" chnl="15"/><!-- 玩 --><char id="29983" x="302" y="40" width="41" height="39" xoffset="0" yoffset="-1" xadvance="42" page="0" chnl="15"/><!-- 生 --><char id="29992" x="467" y="41" width="39" height="39" xoffset="0" yoffset="0" xadvance="42" page="0" chnl="15"/><!-- 用 --><char id="30340" x="344" y="168" width="40" height="41" xoffset="1" yoffset="-2" xadvance="42" page="0" chnl="15"/><!-- 的 --><char id="30424" x="260" y="374" width="41" height="40" xoffset="1" yoffset="-2" xadvance="42" page="0" chnl="15"/><!-- 盘 --><char id="30830" x="218" y="379" width="41" height="41" xoffset="0" yoffset="-2" xadvance="42" page="0" chnl="15"/><!-- 确 --><char id="31034" x="426" y="40" width="40" height="39" xoffset="1" yoffset="0" xadvance="42" page="0" chnl="15"/><!-- 示 --><char id="31181" x="260" y="415" width="41" height="40" xoffset="0" yoffset="-1" xadvance="42" page="0" chnl="15"/><!-- 种 --><char id="31186" x="132" y="533" width="42" height="40" xoffset="0" yoffset="-1" xadvance="42" page="0" chnl="15"/><!-- 秒 --><char id="31227" x="46" y="0" width="42" height="41" xoffset="0" yoffset="-2" xadvance="42" page="0" chnl="15"/><!-- 移 --><char id="31243" x="132" y="574" width="42" height="40" xoffset="0" yoffset="-1" xadvance="42" page="0" chnl="15"/><!-- 程 --><char id="31354" x="385" y="451" width="40" height="40" xoffset="1" yoffset="-2" xadvance="42" page="0" chnl="15"/><!-- 空 --><char id="31435" x="175" y="119" width="42" height="38" xoffset="0" yoffset="-1" xadvance="42" page="0" chnl="15"/><!-- 立 --><char id="31561" x="344" y="252" width="40" height="41" xoffset="1" yoffset="-2" xadvance="42" page="0" chnl="15"/><!-- 等 --><char id="31616" x="344" y="210" width="40" height="41" xoffset="1" yoffset="-2" xadvance="42" page="0" chnl="15"/><!-- 简 --><char id="32423" x="46" y="462" width="42" height="41" xoffset="0" yoffset="-2" xadvance="42" page="0" chnl="15"/><!-- 级 --><char id="32440" x="46" y="504" width="42" height="41" xoffset="0" yoffset="-2" xadvance="42" page="0" chnl="15"/><!-- 纸 --><char id="32467" x="89" y="210" width="42" height="41" xoffset="0" yoffset="-2" xadvance="42" page="0" chnl="15"/><!-- 结 --><char id="32479" x="218" y="211" width="41" height="41" xoffset="1" yoffset="-2" xadvance="42" page="0" chnl="15"/><!-- 统 --><char id="32487" x="132" y="451" width="42" height="40" xoffset="0" yoffset="-2" xadvance="42" page="0" chnl="15"/><!-- 继 --><char id="32493" x="0" y="334" width="42" height="42" xoffset="0" yoffset="-2" xadvance="42" page="0" chnl="15"/><!-- 续 --><char id="32622" x="426" y="0" width="40" height="39" xoffset="1" yoffset="0" xadvance="42" page="0" chnl="15"/><!-- 置 --><char id="32972" x="344" y="84" width="40" height="41" xoffset="1" yoffset="-2" xadvance="42" page="0" chnl="15"/><!-- 背 --><char id="32988" x="132" y="41" width="42" height="40" xoffset="0" yoffset="-1" xadvance="42" page="0" chnl="15"/><!-- 胜 --><char id="33258" x="507" y="118" width="32" height="41" xoffset="5" yoffset="-2" xadvance="42" page="0" chnl="15"/><!-- 自 --><char id="33267" x="426" y="437" width="40" height="38" xoffset="1" yoffset="0" xadvance="42" page="0" chnl="15"/><!-- 至 --><char id="33394" x="260" y="42" width="41" height="41" xoffset="0" yoffset="-2" xadvance="42" page="0" chnl="15"/><!-- 色 --><char id="33457" x="260" y="0" width="41" height="41" xoffset="1" yoffset="-2" xadvance="42" page="0" chnl="15"/><!-- 花 --><char id="33719" x="344" y="126" width="40" height="41" xoffset="1" yoffset="-2" xadvance="42" page="0" chnl="15"/><!-- 获 --><char id="34523" x="89" y="126" width="42" height="41" xoffset="0" yoffset="-2" xadvance="42" page="0" chnl="15"/><!-- 蛛 --><char id="34584" x="175" y="510" width="41" height="42" xoffset="0" yoffset="-2" xadvance="42" page="0" chnl="15"/><!-- 蜘 --><char id="35268" x="218" y="43" width="41" height="41" xoffset="1" yoffset="-1" xadvance="42" page="0" chnl="15"/><!-- 规 --><char id="35299" x="0" y="248" width="42" height="42" xoffset="0" yoffset="-2" xadvance="42" page="0" chnl="15"/><!-- 解 --><char id="35745" x="46" y="84" width="42" height="41" xoffset="0" yoffset="-2" xadvance="42" page="0" chnl="15"/><!-- 计 --><char id="35774" x="0" y="545" width="42" height="41" xoffset="0" yoffset="-1" xadvance="42" page="0" chnl="15"/><!-- 设 --><char id="35797" x="89" y="504" width="42" height="41" xoffset="0" yoffset="-2" xadvance="42" page="0" chnl="15"/><!-- 试 --><char id="35831" x="89" y="546" width="42" height="40" xoffset="0" yoffset="-1" xadvance="42" page="0" chnl="15"/><!-- 请 --><char id="36133" x="175" y="338" width="41" height="42" xoffset="1" yoffset="-2" xadvance="42" page="0" chnl="15"/><!-- 败 --><char id="36187" x="302" y="249" width="40" height="42" xoffset="1" yoffset="-2" xadvance="42" page="0" chnl="15"/><!-- 赛 --><char id="36194" x="0" y="119" width="42" height="42" xoffset="0" yoffset="-2" xadvance="42" page="0" chnl="15"/><!-- 赢 --><char id="36341" x="46" y="252" width="42" height="41" xoffset="0" yoffset="-2" xadvance="42" page="0" chnl="15"/><!-- 践 --><char id="36733" x="218" y="463" width="41" height="41" xoffset="1" yoffset="-2" xadvance="42" page="0" chnl="15"/><!-- 载 --><char id="36755" x="89" y="378" width="42" height="41" xoffset="0" yoffset="-2" xadvance="42" page="0" chnl="15"/><!-- 输 --><char id="36798" x="260" y="168" width="41" height="41" xoffset="1" yoffset="-1" xadvance="42" page="0" chnl="15"/><!-- 达 --><char id="36820" x="344" y="462" width="40" height="41" xoffset="1" yoffset="-1" xadvance="42" page="0" chnl="15"/><!-- 返 --><char id="36824" x="302" y="503" width="40" height="41" xoffset="1" yoffset="-1" xadvance="42" page="0" chnl="15"/><!-- 还 --><char id="36992" x="175" y="209" width="41" height="42" xoffset="1" yoffset="-2" xadvance="42" page="0" chnl="15"/><!-- 邀 --><char id="37325" x="385" y="164" width="40" height="40" xoffset="1" yoffset="-1" xadvance="42" page="0" chnl="15"/><!-- 重 --><char id="38381" x="467" y="287" width="38" height="41" xoffset="2" yoffset="-2" xadvance="42" page="0" chnl="15"/><!-- 闭 --><char id="38386" x="467" y="245" width="38" height="41" xoffset="2" yoffset="-2" xadvance="42" page="0" chnl="15"/><!-- 闲 --><char id="38388" x="467" y="203" width="38" height="41" xoffset="2" yoffset="-2" xadvance="42" page="0" chnl="15"/><!-- 间 --><char id="38590" x="89" y="252" width="42" height="41" xoffset="0" yoffset="-2" xadvance="42" page="0" chnl="15"/><!-- 难 --><char id="38663" x="344" y="504" width="40" height="40" xoffset="1" yoffset="0" xadvance="42" page="0" chnl="15"/><!-- 震 --><char id="38754" x="426" y="200" width="40" height="39" xoffset="1" yoffset="0" xadvance="42" page="0" chnl="15"/><!-- 面 --><char id="39034" x="132" y="246" width="42" height="40" xoffset="0" yoffset="-1" xadvance="42" page="0" chnl="15"/><!-- 顺 --><char id="39064" x="175" y="0" width="42" height="39" xoffset="0" yoffset="0" xadvance="42" page="0" chnl="15"/><!-- 题 --><char id="39640" x="302" y="545" width="40" height="41" xoffset="1" yoffset="-2" xadvance="42" page="0" chnl="15"/><!-- 高 --><char id="65281" x="122" y="587" width="9" height="32" xoffset="6" yoffset="3" xadvance="42" page="0" chnl="15"/><!-- ！ --><char id="65292" x="74" y="588" width="10" height="16" xoffset="3" yoffset="27" xadvance="42" page="0" chnl="15"/><!-- ， --><char id="65306" x="585" y="456" width="9" height="24" xoffset="6" yoffset="7" xadvance="42" page="0" chnl="15"/><!-- ： --><char id="65311" x="597" y="193" width="21" height="33" xoffset="0" yoffset="2" xadvance="42" page="0" chnl="15"/><!-- ？ --></chars><kernings count="25"><kerning first="53" second="95" amount="-1"/><kerning first="54" second="95" amount="-2"/><kerning first="55" second="52" amount="-2"/><kerning first="55" second="55" amount="1"/><kerning first="55" second="56" amount="-1"/><kerning first="55" second="95" amount="-6"/><kerning first="55" second="47" amount="-1"/><kerning first="55" second="64" amount="-1"/><kerning first="55" second="35" amount="-2"/><kerning first="55" second="38" amount="-2"/><kerning first="56" second="65" amount="-1"/><kerning first="56" second="95" amount="-1"/><kerning first="63" second="52" amount="-1"/><kerning first="95" second="49" amount="-4"/><kerning first="95" second="51" amount="-2"/><kerning first="95" second="52" amount="-2"/><kerning first="95" second="53" amount="-2"/><kerning first="95" second="56" amount="-2"/><kerning first="95" second="57" amount="-2"/><kerning first="95" second="103" amount="1"/><kerning first="95" second="112" amount="2"/><kerning first="47" second="52" amount="-1"/><kerning first="64" second="55" amount="-1"/><kerning first="35" second="52" amount="-1"/><kerning first="38" second="49" amount="-1"/></kernings></font>